CHANGELOG.txt
LICENSE.txt
MANIFEST.in
README.txt
__init__.py
keys.py
setup.py
lnm.egg-info/PKG-INFO
lnm.egg-info/SOURCES.txt
lnm.egg-info/dependency_links.txt
lnm.egg-info/requires.txt
lnm.egg-info/top_level.txt