Metadata-Version: 1.1
Name: lnm
Version: 0.0.1
Summary: A Lipa na M-Pesa Client Payment initiator package
Home-page: UNKNOWN
Author: LazyGeek
Author-email: vincentedepaulo@gmail.com
License: MIT
Keywords: lipa na mpesa
Platform: UNKNOWN
Classifier: Development Status :: 5 - Production/Stable
Classifier: Intended Audience :: Developers
Classifier: Operating System :: Microsoft :: Windows :: Windows 10
Classifier: License :: OSI Approved :: MIT License
Classifier: Programming Language :: Python :: 3
